softhauz/__init__.py
softhauz/asgi.py
softhauz/main.py
softhauz/settings.py
softhauz/urls.py
softhauz/wsgi.py
softhauz-0.0.8.dist-info/LICENSE
softhauz-0.0.8.dist-info/METADATA
softhauz-0.0.8.dist-info/WHEEL
softhauz-0.0.8.dist-info/top_level.txt
softhauz-0.0.8.dist-info/RECORD
