Metadata-Version: 2.1
Name: softhauz
Version: 0.0.8
Summary: [FOR EXTERNAL PROJECTS] This python package, primarily created for the stabilization and support of the current Softhauz system, offers various visualization and web interface tools for calculus, chemistry, and data science, with optional localization for the currently available language codes: ENG, FRA, SPA, KOR, and JPN. 
Author: Karen Urate
Author-email: Karen Urate <karen.urate@softhauz.ca>
License: MIT
Project-URL: Homepage, https://softhauz.ca
Requires-Python: >=3.11
License-File: LICENSE
Requires-Dist: matplotlib==3.10.7
Requires-Dist: numpy>=1.26.2
Requires-Dist: sympy==1.14.0
Requires-Dist: chempy>=0.10.1
Requires-Dist: Faker>=35.2.0
Requires-Dist: django-countries==7.6.1
Requires-Dist: django-auto-logout==0.5.1
Requires-Dist: python-dotenv==1.0.1
